requirements.txt
setup.py
pypi_rss/__init__.py
pypi_rss.egg-info/PKG-INFO
pypi_rss.egg-info/SOURCES.txt
pypi_rss.egg-info/dependency_links.txt
pypi_rss.egg-info/requires.txt
pypi_rss.egg-info/top_level.txt