Metadata-Version: 2.1
Name: pypi-rss
Version: 2020.7.1
Summary: pypi.org rss utils
Home-page: https://github.com/andrewp-as-is/pypi-rss.py
License: Unlicense
Keywords: pypi.org rss
Platform: UNKNOWN
Classifier: License :: Public Domain
Classifier: Operating System :: OS Independent
Classifier: Programming Language :: Python :: 3
